<?xml version="1.0" encoding="UTF-8"?>
<LanguageData>

  <Cut.label>Skärskada</Cut.label>
  <Cut.deathMessage>{0} avled av sina skärskador.</Cut.deathMessage>

  <Crush.label>Krosskada</Crush.label>
  <Crush.deathMessage>{0} krossades till ihjäl.</Crush.deathMessage>

  <Blunt.label>Slag</Blunt.label>
  <Blunt.deathMessage>{0} har slagits ihjäl.</Blunt.deathMessage>

  <Stab.label>Hugg</Stab.label>
  <Stab.deathMessage>{0} höggs ihjäl.</Stab.deathMessage>

  <Bullet.label>Kula</Bullet.label>
  <Bullet.deathMessage>{0} sköts ihjäl.</Bullet.deathMessage>

  <Arrow.label>Pil</Arrow.label>
  <Arrow.deathMessage>{0} sköts ihjäl.</Arrow.deathMessage>

  <Scratch.label>Rivsår</Scratch.label>
  <Scratch.deathMessage>{0} har rivits ihjäl.</Scratch.deathMessage>

  <Bite.label>Bett</Bite.label>
  <Bite.deathMessage>{0} bets ihjäl.</Bite.deathMessage>

  <ToxicBite.label>Giftigt bett</ToxicBite.label>
  <ToxicBite.deathMessage>{0} dog av förgiftning.</ToxicBite.deathMessage>

  <Bomb.label>Explosion</Bomb.label>
  <Bomb.deathMessage>{0} omkom i en explosion.</Bomb.deathMessage>

  <Flame.label>Eld</Flame.label>
  <Flame.deathMessage>{0} omkom i en brand.</Flame.deathMessage>

  <Frostbite.label>Frostskada</Frostbite.label>
  <Frostbite.deathMessage>{0} frös ihjäl.</Frostbite.deathMessage>

  <SurgicalCut.label>Kirurgiskt snitt</SurgicalCut.label>
  <SurgicalCut.deathMessage>{0} avled under ett kirurgiskt ingrepp.</SurgicalCut.deathMessage>

</LanguageData>
